CEP_por_endereco/__init__.py
CEP_por_endereco/cep_finder.py
CEP_por_endereco_completo-0.1.8.dist-info/LICENSE
CEP_por_endereco_completo-0.1.8.dist-info/METADATA
CEP_por_endereco_completo-0.1.8.dist-info/WHEEL
CEP_por_endereco_completo-0.1.8.dist-info/top_level.txt
CEP_por_endereco_completo-0.1.8.dist-info/RECORD
